scriptcrypt/LICENSE
scriptcrypt/__init__.py
scriptcrypt/__main__.py
scriptcrypt/envars.py
scriptcrypt/jsonhandlers.py
scriptcrypt/messages.py
scriptcrypt/populate.py
scriptcrypt/tmpfl.py
scriptcrypt/validation.py
scriptcrypt/version.py
scriptcrypt/completion/bash/bash_completion
scriptcrypt/completion/bash/scriptcrypt
scriptcrypt/completion/zsh/_scriptcrypt
scriptcrypt/data/scriptcrypt.db
scriptcrypt/db/__init__.py
scriptcrypt/db/db.py
scriptcrypt/db/db2json.py
scriptcrypt/db/json2db.py
scriptcrypt/db/schema.py
scriptcrypt/mcurses/__init__.py
scriptcrypt/mcurses/cursobjs.py
scriptcrypt/mcurses/interface.py
scriptcrypt-17.7.dist-info/DESCRIPTION.rst
scriptcrypt-17.7.dist-info/METADATA
scriptcrypt-17.7.dist-info/RECORD
scriptcrypt-17.7.dist-info/WHEEL
scriptcrypt-17.7.dist-info/entry_points.txt
scriptcrypt-17.7.dist-info/metadata.json
scriptcrypt-17.7.dist-info/top_level.txt
