Metadata-Version: 2.0
Name: scriptcrypt
Version: 17.7
Summary: Custom script notebook
Home-page: https://bitbucket.com/seregaxvm/scriptcrypt
Author: S.V. Matsievskiy
Author-email: matsievskiysv@gmail.com
License: GPLv3+
Keywords: script database
Platform: UNKNOWN
Classifier: Development Status :: 3 - Alpha
Classifier: Intended Audience :: End Users/Desktop
Classifier: Topic :: Database :: Front-Ends
Classifier: License :: OSI Approved :: GNU General Public License v3 or later (GPLv3+)
Classifier: Environment :: Console :: Curses
Classifier: Natural Language :: English
Classifier: Operating System :: POSIX :: Linux
Classifier: Programming Language :: Python :: 3.5
Requires-Dist: docopt
Requires-Dist: sqlalchemy
Provides-Extra: dev
Requires-Dist: check-manifest; extra == 'dev'
Provides-Extra: test
Requires-Dist: nose; extra == 'test'
